TimeV2/__init__.py
TimeV2/time2.py
TimeV2-0.0.9.dist-info/LICENSE
TimeV2-0.0.9.dist-info/METADATA
TimeV2-0.0.9.dist-info/WHEEL
TimeV2-0.0.9.dist-info/top_level.txt
TimeV2-0.0.9.dist-info/RECORD
